langguard/__init__.py
langguard/agent.py
langguard/models.py
langguard-0.7.0.dist-info/licenses/LICENSE
langguard-0.7.0.dist-info/METADATA
langguard-0.7.0.dist-info/WHEEL
langguard-0.7.0.dist-info/top_level.txt
langguard-0.7.0.dist-info/RECORD
