Metadata-Version: 2.4
Name: langguard
Version: 0.7.0
Summary: A Python library for language security
Home-page: https://github.com/aprzy/langguard-python
Author: Your Name
Author-email: Andrew Jon Przybilla <andrewprzy@pm.me>
License: MIT License
Project-URL: Homepage, https://github.com/langguard/langguard-python
Project-URL: Repository, https://github.com/langguard/langguard-python
Project-URL: Issues, https://github.com/langguard/langguard-python/issues
Keywords: security,language,protection
Classifier: Development Status :: 3 - Alpha
Classifier: Intended Audience :: Developers
Classifier: License :: OSI Approved :: MIT License
Classifier: Programming Language :: Python :: 3
Classifier: Programming Language :: Python :: 3.11
Classifier: Programming Language :: Python :: 3.12
Requires-Python: >=3.11
License-File: LICENSE
Requires-Dist: requests>=2.25.0
Requires-Dist: pydantic>=1.8.0
Requires-Dist: backoff>=2.2.1
Provides-Extra: dev
Requires-Dist: pytest>=7.0.0; extra == "dev"
Requires-Dist: pytest-cov>=4.0.0; extra == "dev"
Requires-Dist: black>=23.0.0; extra == "dev"
Dynamic: author
Dynamic: home-page
Dynamic: license-file
Dynamic: requires-python
